jupyter_jaeger/__init__.py
jupyter_jaeger/jaeger.svg
jupyter_jaeger-1.0.3.dist-info/entry_points.txt
jupyter_jaeger-1.0.3.dist-info/LICENSE
jupyter_jaeger-1.0.3.dist-info/WHEEL
jupyter_jaeger-1.0.3.dist-info/METADATA
jupyter_jaeger-1.0.3.dist-info/RECORD
