Metadata-Version: 2.1
Name: jupyter_jaeger
Version: 1.0.3
Summary: Provides jupyter server proxy endpoints for launching Jaeger.
Home-page: https://github.com/Quansight/jupyter-browser
License: UNKNOWN
Author: Saul Shanabrook
Author-email: saul@quansight.com
Requires-Python: >=3.6
Classifier: License :: OSI Approved :: MIT License
Requires-Dist: jaeger_browser
Requires-Dist: notebook
Requires-Dist: jupyter-server-proxy
